LICENSE
MANIFEST.in
README.rst
setup.cfg
setup.py
bin/chardetect.py
charade/__init__.py
charade/big5freq.py
charade/big5prober.py
charade/chardistribution.py
charade/charsetgroupprober.py
charade/charsetprober.py
charade/codingstatemachine.py
charade/compat.py
charade/constants.py
charade/escprober.py
charade/escsm.py
charade/eucjpprober.py
charade/euckrfreq.py
charade/euckrprober.py
charade/euctwfreq.py
charade/euctwprober.py
charade/gb2312freq.py
charade/gb2312prober.py
charade/hebrewprober.py
charade/jisfreq.py
charade/jpcntx.py
charade/langbulgarianmodel.py
charade/langcyrillicmodel.py
charade/langgreekmodel.py
charade/langhebrewmodel.py
charade/langhungarianmodel.py
charade/langthaimodel.py
charade/latin1prober.py
charade/mbcharsetprober.py
charade/mbcsgroupprober.py
charade/mbcssm.py
charade/sbcharsetprober.py
charade/sbcsgroupprober.py
charade/sjisprober.py
charade/universaldetector.py
charade/utf8prober.py
charade.egg-info/PKG-INFO
charade.egg-info/SOURCES.txt
charade.egg-info/dependency_links.txt
charade.egg-info/top_level.txt