Metadata-Version: 1.0
Name: charade
Version: 1.0.0
Summary: Universal encoding detector for python 2 and 3
Home-page: https://github.com/sigmavirus24/charade
Author: Ian Cordasco
Author-email: graffatcolmingov@gmail.com
License: LGPL
Keywords: encoding,i18n,xml
Platform: UNKNOWN
Classifier: Development Status :: 4 - Beta
Classifier: Environment :: Other Environment
Classifier: Intended Audience :: Developers
Classifier: License :: OSI Approved :: GNU Library or Lesser General Public License (LGPL)
Classifier: Operating System :: OS Independent
Classifier: Programming Language :: Python
Classifier: Topic :: Software Development :: Libraries :: Python Modules
Classifier: Topic :: Text Processing :: Linguistic
